runrestic/__init__.py
runrestic/metrics/__init__.py
runrestic/metrics/prometheus.py
runrestic/restic/__init__.py
runrestic/restic/installer.py
runrestic/restic/output_parsing.py
runrestic/restic/runner.py
runrestic/restic/shell.py
runrestic/restic/tools.py
runrestic/runrestic/__init__.py
runrestic/runrestic/configuration.py
runrestic/runrestic/runrestic.py
runrestic/runrestic/schema.json
runrestic/runrestic/tools.py
runrestic-0.5.29.dist-info/LICENSE
runrestic-0.5.29.dist-info/METADATA
runrestic-0.5.29.dist-info/WHEEL
runrestic-0.5.29.dist-info/entry_points.txt
runrestic-0.5.29.dist-info/RECORD
