Metadata-Version: 2.3
Name: runrestic
Version: 0.5.29
Summary: A wrapper script for Restic backup software that inits, creates, prunes and checks backups
License: GPL-3.0+
Keywords: backup
Author: Andreas Nüßlein
Author-email: andreas@nuessle.in
Requires-Python: >3.8
Classifier: Development Status :: 4 - Beta
Classifier: Environment :: Console
Classifier: Intended Audience :: System Administrators
Classifier: License :: OSI Approved :: GNU General Public License v3 or later (GPLv3+)
Classifier: Programming Language :: Python
Classifier: Programming Language :: Python :: 3
Classifier: Programming Language :: Python :: 3.9
Classifier: Programming Language :: Python :: 3.10
Classifier: Programming Language :: Python :: 3.11
Classifier: Programming Language :: Python :: 3.12
Classifier: Programming Language :: Python :: 3.13
Classifier: Topic :: Security :: Cryptography
Classifier: Topic :: System :: Archiving :: Backup
Requires-Dist: jsonschema (>3.0)
Requires-Dist: requests (>2.27.1)
Requires-Dist: toml (>=0.10,<0.11)
Project-URL: Homepage, https://github.com/sinnwerkstatt/runrestic
Project-URL: Repository, https://github.com/sinnwerkstatt/runrestic
